seplot/README.md
seplot/__init__.py
seplot/grapher.py
seplot/kw_dictionaries.py
seplot/seplot.py
seplot/seploter.py
seplot/style_dictionaries.py
seplot/styler.py
sio_tools/__init__.py
sio_tools/sio_tools.py
sio_tools-0.1.12.dist-info/LICENCE.md
sio_tools-0.1.12.dist-info/METADATA
sio_tools-0.1.12.dist-info/WHEEL
sio_tools-0.1.12.dist-info/top_level.txt
sio_tools-0.1.12.dist-info/RECORD
