Metadata-Version: 2.1
Name: sio-tools
Version: 0.1.12
Summary: I/O tools for seplot and other python projects
Home-page: https://github.com/SergeDmi/Python-Tools/
Author: Serge Dmitrieff
Author-email: UNKNOWN
License: UNKNOWN
Platform: UNKNOWN
Requires-Dist: numpy
